lunette/__init__.py
lunette/_registry.py
lunette/analysis.py
lunette/cli.py
lunette/client.py
lunette/hooks.py
lunette/inspect_sandbox.py
lunette/logger.py
lunette/sandbox.py
lunette/models/__init__.py
lunette/models/investigation.py
lunette/models/messages.py
lunette/models/run.py
lunette/models/trajectory.py
lunette/presets/__init__.py
lunette/presets/swebench.yaml
lunette/tracing/__init__.py
lunette/tracing/context.py
lunette/tracing/span_collector.py
lunette/tracing/span_converter.py
lunette/tracing/tracer.py
lunette_sdk-0.2.2.dist-info/METADATA
lunette_sdk-0.2.2.dist-info/WHEEL
lunette_sdk-0.2.2.dist-info/entry_points.txt
lunette_sdk-0.2.2.dist-info/top_level.txt
lunette_sdk-0.2.2.dist-info/RECORD
