Metadata-Version: 2.4
Name: lunette-sdk
Version: 0.2.2
Requires-Python: >=3.10
Requires-Dist: inspect-ai
Requires-Dist: httpx>=0.27.0
Requires-Dist: pyyaml>=6.0
Requires-Dist: opentelemetry-api>=1.39.0
Requires-Dist: opentelemetry-sdk>=1.39.0
Requires-Dist: openai>=2.7.1
Requires-Dist: opentelemetry-instrumentation-openai>=0.49.6
Requires-Dist: anthropic>=0.50.0
Requires-Dist: opentelemetry-instrumentation-anthropic>=0.37.0
